{
    "details": {
        "aileron": {
            "name": "Элерон",
            "desc": "null"
        },
        "fuselage001": {
            "name": "Кабина самолета",
            "desc": "null"
        },
        "fuselage001_1": {
            "name": "Кабина самолета",
            "desc": "null"
        },
        "elevator": {
            "name": "Подъемники",
            "desc": "null"
        },
        "engines_1": {
            "name": "Двигатель",
            "desc": "Двигатель Williams International FJ44-4A с электронным управлением (FADEC) дебютирует на CJ4. Каждый из двух двигателей обеспечивает тягу в 3400 фунтов (сниженную с 3600 фунтов) по сравнению с 2820 фунтами FJ44-3A CJ3.\nFJ44-4A обладает лучшим соотношением тяги к массе в своем классе тяги и включает в себя несколько запатентованных аэродинамических улучшений, которые позволяют значительно снизить расход топлива." 
        },
        "engines_2": {
            "name": "Двигатель",
            "desc": "Двигатель Williams International FJ44-4A с электронным управлением (FADEC) дебютирует на CJ4. Каждый из двух двигателей обеспечивает тягу в 3400 фунтов (сниженную с 3600 фунтов) по сравнению с 2820 фунтами FJ44-3A CJ3.\nFJ44-4A обладает лучшим соотношением тяги к массе в своем классе тяги и включает в себя несколько запатентованных аэродинамических улучшений, которые позволяют значительно снизить расход топлива." 
        },
        "engines_3": {
            "name": "Двигатель",
            "desc": "Двигатель Williams International FJ44-4A с электронным управлением (FADEC) дебютирует на CJ4. Каждый из двух двигателей обеспечивает тягу в 3400 фунтов (сниженную с 3600 фунтов) по сравнению с 2820 фунтами FJ44-3A CJ3.\nFJ44-4A обладает лучшим соотношением тяги к массе в своем классе тяги и включает в себя несколько запатентованных аэродинамических улучшений, которые позволяют значительно снизить расход топлива." 
        },
        "flaps": {
            "name": "Закрылки",
            "desc": "null"
        },
        "fuselage_1": {
            "name": "Корпус",
            "desc": "null"
        },
        "fuselage_2": {
            "name": "Корпус",
            "desc": "null"
        },
        "horizontal-stabilizer": {
            "name": "Горизонтальные стабилизаторы",
            "desc": "null"
        },
        "vertical-stabilizer": {
            "name": "Вертикальные стабилизаторы",
            "desc": "null"
        },
        "rudder": {
            "name": "Руль направления",
            "desc": "null"
        },
        "wheels_1": {
            "name": "Шасси",
            "desc": "null"
        },
        "wheels_2": {
            "name": "Шасси",
            "desc": "null"
        },
        "wheels_3": {
            "name": "Шасси",
            "desc": "null"
        },
        "wings": {
            "name": "Крылья",
            "desc": "null"
        }
    }
}